setup.cfg
setup.py
mpl_aea/__init__.py
mpl_aea/aea.py
mpl_aea/collections.py
mpl_aea/geo.py
mpl_aea/healpix.py
mpl_aea/monkey.py
mpl_aea/version.py
mpl_aea.egg-info/PKG-INFO
mpl_aea.egg-info/SOURCES.txt
mpl_aea.egg-info/dependency_links.txt
mpl_aea.egg-info/requires.txt
mpl_aea.egg-info/top_level.txt
mpl_aea.egg-info/zip-safe