Metadata-Version: 1.0
Name: mpl-aea
Version: 0.0.4
Summary: AEA Projection for Matplotlib derived from skywalker 
Home-page: http://github.com/rainwoodman/mpl_aea
Author: Yu Feng
Author-email: rainwoodman@gmail.com
License: GPL3
Platform: UNKNOWN
